clouvel/__init__.py
clouvel/__main__.py
clouvel/analytics.py
clouvel/api_client.py
clouvel/license_common.py
clouvel/license_free.py
clouvel/pro_downloader.py
clouvel/server.py
clouvel/trial.py
clouvel/ui.py
clouvel/version_check.py
clouvel/messages/__init__.py
clouvel/messages/en.py
clouvel/templates/api/detailed.md
clouvel/templates/api/lite.md
clouvel/templates/api/standard.md
clouvel/templates/chrome-ext/detailed.md
clouvel/templates/chrome-ext/lite.md
clouvel/templates/chrome-ext/standard.md
clouvel/templates/cli/detailed.md
clouvel/templates/cli/lite.md
clouvel/templates/cli/standard.md
clouvel/templates/discord-bot/detailed.md
clouvel/templates/discord-bot/lite.md
clouvel/templates/discord-bot/standard.md
clouvel/templates/guides/documentation-guide.md
clouvel/templates/landing-page/detailed.md
clouvel/templates/landing-page/lite.md
clouvel/templates/landing-page/standard.md
clouvel/templates/saas/detailed.md
clouvel/templates/saas/lite.md
clouvel/templates/saas/standard.md
clouvel/templates/web-app/detailed.md
clouvel/templates/web-app/lite.md
clouvel/templates/web-app/standard.md
clouvel/tools/__init__.py
clouvel/tools/agents.py
clouvel/tools/architecture.py
clouvel/tools/core.py
clouvel/tools/docs.py
clouvel/tools/hooks.py
clouvel/tools/install.py
clouvel/tools/knowledge.py
clouvel/tools/meeting.py
clouvel/tools/meeting_data.py
clouvel/tools/meeting_feedback.py
clouvel/tools/meeting_kb.py
clouvel/tools/meeting_personalization.py
clouvel/tools/meeting_prompt.py
clouvel/tools/meeting_tuning.py
clouvel/tools/planning.py
clouvel/tools/proactive.py
clouvel/tools/rules.py
clouvel/tools/setup.py
clouvel/tools/ship.py
clouvel/tools/start.py
clouvel/tools/tracking.py
clouvel/tools/verify.py
clouvel/utils/__init__.py
clouvel/utils/entitlements.py
clouvel-3.0.2.dist-info/METADATA
clouvel-3.0.2.dist-info/WHEEL
clouvel-3.0.2.dist-info/entry_points.txt
clouvel-3.0.2.dist-info/RECORD
