Metadata-Version: 2.4
Name: clouvel
Version: 3.0.2
Summary: 바이브코딩 프로세스를 강제하는 MCP 서버 - PRD 없으면 코딩 없다
Project-URL: Homepage, https://github.com/Whitening-Sinabro/clouvel
Project-URL: Repository, https://github.com/Whitening-Sinabro/clouvel
Project-URL: Issues, https://github.com/Whitening-Sinabro/clouvel/issues
Author: SINABRO
License-Expression: MIT
Keywords: claude-code,documentation,mcp,prd,shovel,vibe-coding
Classifier: Development Status :: 4 - Beta
Classifier: Intended Audience :: Developers
Classifier: License :: OSI Approved :: MIT License
Classifier: Programming Language :: Python :: 3.10
Classifier: Programming Language :: Python :: 3.11
Classifier: Programming Language :: Python :: 3.12
Classifier: Programming Language :: Python :: 3.13
Requires-Python: >=3.10
Requires-Dist: mcp>=1.0.0
Requires-Dist: pydantic>=2.0.0
Requires-Dist: requests>=2.25.0
Provides-Extra: anthropic
Requires-Dist: anthropic>=0.18.0; extra == 'anthropic'
Provides-Extra: dynamic
Requires-Dist: anthropic>=0.18.0; extra == 'dynamic'
Requires-Dist: python-dotenv>=1.0.0; extra == 'dynamic'
Provides-Extra: encryption
Requires-Dist: cryptography>=41.0.0; extra == 'encryption'
Provides-Extra: full
Requires-Dist: anthropic>=0.18.0; extra == 'full'
Requires-Dist: chromadb>=0.4.0; extra == 'full'
Requires-Dist: cryptography>=41.0.0; extra == 'full'
Requires-Dist: python-dotenv>=1.0.0; extra == 'full'
Requires-Dist: rich>=13.0.0; extra == 'full'
Requires-Dist: sentence-transformers>=2.2.0; extra == 'full'
Provides-Extra: ui
Requires-Dist: rich>=13.0.0; extra == 'ui'
Provides-Extra: vector
Requires-Dist: chromadb>=0.4.0; extra == 'vector'
Requires-Dist: sentence-transformers>=2.2.0; extra == 'vector'
